LICENSE
MANIFEST.in
README.md
pyproject.toml
setup.py
/home/runner/work/judge-server/judge-server/dmoj/cptbox/_cptbox.cpp
/home/runner/work/judge-server/judge-server/dmoj/cptbox/helper.cpp
/home/runner/work/judge-server/judge-server/dmoj/cptbox/ptdebug.cpp
/home/runner/work/judge-server/judge-server/dmoj/cptbox/ptdebug_arm.cpp
/home/runner/work/judge-server/judge-server/dmoj/cptbox/ptdebug_arm64.cpp
/home/runner/work/judge-server/judge-server/dmoj/cptbox/ptdebug_freebsd_x64.cpp
/home/runner/work/judge-server/judge-server/dmoj/cptbox/ptdebug_x64.cpp
/home/runner/work/judge-server/judge-server/dmoj/cptbox/ptdebug_x86.cpp
/home/runner/work/judge-server/judge-server/dmoj/cptbox/ptproc.cpp
dmoj/__init__.py
dmoj/__main__.py
dmoj/citest.py
dmoj/cli.py
dmoj/config.py
dmoj/control.py
dmoj/error.py
dmoj/judge.py
dmoj/judgeenv.py
dmoj/main.py
dmoj/monitor.py
dmoj/packet.py
dmoj/problem.py
dmoj/result.py
dmoj/sysinfo.py
dmoj/testsuite.py
dmoj.egg-info/PKG-INFO
dmoj.egg-info/SOURCES.txt
dmoj.egg-info/dependency_links.txt
dmoj.egg-info/entry_points.txt
dmoj.egg-info/requires.txt
dmoj.egg-info/top_level.txt
dmoj/checkers/__init__.py
dmoj/checkers/_checker.c
dmoj/checkers/bridged.py
dmoj/checkers/easy.py
dmoj/checkers/floats.py
dmoj/checkers/floatsabs.py
dmoj/checkers/floatsrel.py
dmoj/checkers/identical.py
dmoj/checkers/linecount.py
dmoj/checkers/linematches.py
dmoj/checkers/rstripped.py
dmoj/checkers/sorted.py
dmoj/checkers/standard.py
dmoj/checkers/unordered.py
dmoj/commands/__init__.py
dmoj/commands/base_command.py
dmoj/commands/diff.py
dmoj/commands/help.py
dmoj/commands/problems.py
dmoj/commands/quit.py
dmoj/commands/rejudge.py
dmoj/commands/resubmit.py
dmoj/commands/show.py
dmoj/commands/submissions.py
dmoj/commands/submit.py
dmoj/commands/test.py
dmoj/contrib/__init__.py
dmoj/contrib/coci.py
dmoj/contrib/default.py
dmoj/contrib/peg.py
dmoj/contrib/testlib.py
dmoj/cptbox/__init__.py
dmoj/cptbox/_cptbox.cpp
dmoj/cptbox/compiler_isolate.py
dmoj/cptbox/ext_freebsd.h
dmoj/cptbox/ext_linux.h
dmoj/cptbox/filesystem_policies.py
dmoj/cptbox/handlers.py
dmoj/cptbox/helper.cpp
dmoj/cptbox/helper.h
dmoj/cptbox/isolate.py
dmoj/cptbox/ptbox.h
