Metadata-Version: 2.1
Name: dmoj
Version: 4.0.1
Summary: The judge component of the DMOJ: Modern Online Judge platform
Home-page: https://github.com/DMOJ/judge-server
Author: DMOJ Team
Author-email: contact@dmoj.ca
License: UNKNOWN
Keywords: online-judge
Platform: UNKNOWN
Classifier: Development Status :: 5 - Production/Stable
Classifier: Environment :: Console
Classifier: Intended Audience :: Developers
Classifier: License :: OSI Approved :: GNU Affero General Public License v3 or later (AGPLv3+)
Classifier: Operating System :: POSIX :: Linux
Classifier: Operating System :: POSIX :: BSD :: FreeBSD
Classifier: Programming Language :: Python
Classifier: Programming Language :: Python :: 3.7
Classifier: Programming Language :: Python :: 3.8
Classifier: Programming Language :: Python :: 3.9
Classifier: Programming Language :: Python :: 3.10
Classifier: Programming Language :: Python :: 3.11
Classifier: Topic :: Education
Classifier: Topic :: Software Development
Provides-Extra: test
License-File: LICENSE
